setup.py
py_pyper.egg-info/PKG-INFO
py_pyper.egg-info/SOURCES.txt
py_pyper.egg-info/dependency_links.txt
py_pyper.egg-info/top_level.txt
pyper/__init__.py
pyper/exceptions.py
pyper/nodes.py