Metadata-Version: 2.1
Name: py-pyper
Version: 0.0.2
Summary: Construct REAPER projects in Python.
Home-page: https://github.com/jamesb93/pyper
Author: James Bradbury
Author-email: jamesbradbury93@gmail.com
License: GLPv3+
Platform: UNKNOWN
